rqueue/__init__.py
rqueue/queue_executor.py
redis_rqueue-1.0.3.dist-info/METADATA
redis_rqueue-1.0.3.dist-info/WHEEL
redis_rqueue-1.0.3.dist-info/top_level.txt
redis_rqueue-1.0.3.dist-info/RECORD
