Metadata-Version: 2.1
Name: redis-rqueue
Version: 1.0.3
Requires-Python: >=3.8
Requires-Dist: redis (==4.5.5)
